recp/__init__.py
recp/cli/__init__.py
recp/cli/main.py
recp/py.typed
recp/utils/__init__.py
recp/utils/apply.py
recp/utils/collections.py
recp/utils/config.py
recp/utils/exceptions.py
recp/utils/io.py
recp/utils/recipe.py
recp-0.1.1.dist-info/WHEEL
recp-0.1.1.dist-info/entry_points.txt
recp-0.1.1.dist-info/METADATA
recp-0.1.1.dist-info/RECORD
