Metadata-Version: 2.3
Name: recp
Version: 0.1.1
Summary: A tool for running command line recipes
Author: Esteban Gómez
Author-email: Esteban Gómez <esteban.gomezmellado@aalto.fi>
License: Attribution-ShareAlike 4.0 International
Requires-Dist: packaging>=25.0
Requires-Dist: platformdirs>=4.5.1
Requires-Dist: pyyaml>=6.0.3
Requires-Dist: mkdocs>=1.6.1 ; extra == 'docs'
Requires-Dist: mkdocstrings-python>=2.0.1 ; extra == 'docs'
Requires-Dist: mkdocs-material>=9.7.1 ; extra == 'docs'
Requires-Dist: ruff>=0.1.9 ; extra == 'lint'
Requires-Python: >=3.11
Project-URL: Home, https://www.github.com/eagomez2/recp
Provides-Extra: docs
Provides-Extra: lint
